deepof/__init__.py
deepof/annotation_utils.py
deepof/arena_utils.py
deepof/config.py
deepof/data.py
deepof/data_loading.py
deepof/data_manager.py
deepof/database_explorer.py
deepof/deepof_train_embeddings.py
deepof/export_video.py
deepof/hypermodels.py
deepof/model_utils.py
deepof/models.py
deepof/post_hoc.py
deepof/sanitycheck.py
deepof/test_objects/test_objects.py
deepof/trained_models/.gitkeep
deepof/trained_models/deepof_supervised/deepof_supervised_huddle_estimator.pkl
deepof/utils.py
deepof/visuals.py
deepof/visuals_utils.py
deepof-0.8.4.dist-info/LICENSE
deepof-0.8.4.dist-info/METADATA
deepof-0.8.4.dist-info/WHEEL
deepof-0.8.4.dist-info/RECORD
