Metadata-Version: 2.1
Name: deepof
Version: 0.8.4
Summary: 
Author: lucas_miranda
Author-email: lucas_miranda@psych.mpg.de
Requires-Python: >=3.9,<3.11
Classifier: Programming Language :: Python :: 3
Classifier: Programming Language :: Python :: 3.9
Classifier: Programming Language :: Python :: 3.10
Requires-Dist: Shapely (>=1.8.4,<2.0.0)
Requires-Dist: av (==12.3.0)
Requires-Dist: catboost (>=1.1.1,<2.0.0)
Requires-Dist: duckdb (==1.2.2)
Requires-Dist: h5py (>=3.7.0,<4.0.0)
Requires-Dist: imageio-ffmpeg (>=0.4.7,<0.5.0)
Requires-Dist: imblearn (>=0.0,<0.1)
Requires-Dist: ipywidgets (>=8.0.2,<9.0.0)
Requires-Dist: joblib (>=1.2.0,<2.0.0)
Requires-Dist: kaleido (==0.2.1)
Requires-Dist: keras (==2.14.0)
Requires-Dist: keras-tcn (>=3.5.0,<4.0.0) ; platform_machine != "arm64" or platform_system == "darwin"
Requires-Dist: keras-tcn-macos (>=1.0,<2.0) ; platform_machine == "arm64" or platform_system == "darwin" or platform_system == "Darwin"
Requires-Dist: keras-tuner (>=1.4.7,<2.0.0)
Requires-Dist: llvmlite (>=0.42.0,<0.43.0)
Requires-Dist: lxml (>=4.9.1,<5.0.0)
Requires-Dist: matplotlib (==3.7.2)
Requires-Dist: moviepy (>=1.0.3,<2.0.0)
Requires-Dist: natsort (==8.4.0)
Requires-Dist: networkx (>=2.8.7,<3.0.0)
Requires-Dist: numba (==0.59.1)
Requires-Dist: numpy (>=1.25.2,<2.0.0)
Requires-Dist: opencv-python (>=4.6.0.66,<5.0.0.0)
Requires-Dist: openpyxl (>=3.0.10,<4.0.0)
Requires-Dist: pandas (>=1.5.0,<2.0.0)
Requires-Dist: pomegranate (==1.0.4)
Requires-Dist: pot (>=0.8.2,<0.9.0)
Requires-Dist: pyarrow (>=17.0.0,<18.0.0)
Requires-Dist: regex (>=2022.9.13,<2023.0.0)
Requires-Dist: scikit-learn (==1.2.0)
Requires-Dist: scipy (==1.9.3)
Requires-Dist: seglearn (>=1.2.5,<2.0.0)
Requires-Dist: segment-anything (>=1.0,<2.0)
Requires-Dist: shap (>=0.44.1,<0.45.0)
Requires-Dist: sleap-io (>=0.0.9,<0.0.10)
Requires-Dist: spektral (==1.3.1)
Requires-Dist: statannotations (>=0.5.0,<0.6.0)
Requires-Dist: statsmodels (>=0.14.2,<0.15.0)
Requires-Dist: tables (==3.8.0) ; platform_machine != "arm64" or platform_system != "darwin" and platform_system != "Darwin"
Requires-Dist: tensorflow (==2.14.1) ; platform_machine != "arm64" or platform_system == "darwin"
Requires-Dist: tensorflow-addons (==0.22.0)
Requires-Dist: tensorflow-io-gcs-filesystem (==0.31.0) ; sys_platform != "darwin" and sys_platform != "Darwin"
Requires-Dist: tensorflow-io-gcs-filesystem (==0.37.1) ; sys_platform == "darwin" or sys_platform == "Darwin"
Requires-Dist: tensorflow-macos (==2.14.1) ; platform_machine == "arm64" or platform_system == "darwin" or platform_system == "Darwin"
Requires-Dist: tensorflow-probability (==0.22.1)
Requires-Dist: tifffile (>=2022.8.12,<2023.0.0)
Requires-Dist: torch (==2.8.0) ; sys_platform != "linux"
Requires-Dist: torch (==2.8.0) ; sys_platform == "linux"
Requires-Dist: torchvision (==0.23.0) ; sys_platform != "linux"
Requires-Dist: torchvision (==0.23.0) ; sys_platform == "linux"
Requires-Dist: tqdm (>=4.64.1,<5.0.0)
Requires-Dist: twine (==5.1.1)
Requires-Dist: umap-learn (>=0.5.3,<0.6.0)
Requires-Dist: xgboost (==2.1.4)
